phractal/__init__.py
phractal/src/__init__.py
phractal/src/_utils.py
phractal/src/phraction.py
phractal/src/validated_cached_property.py
phractal/test/__init__.py
phractal/test/test_cvp.py
phractal/test/test_phraction.py
phractal/test/test_vcp.py
Phractal-1.0.1.dist-info/LICENSE
Phractal-1.0.1.dist-info/METADATA
Phractal-1.0.1.dist-info/WHEEL
Phractal-1.0.1.dist-info/top_level.txt
Phractal-1.0.1.dist-info/RECORD
