Metadata-Version: 2.1
Name: Phractal
Version: 1.0.1
Summary: A tool for creating HTML documents programmatically with Python
Home-page: https://github.com/Hauteclere/phractal
Author: Hauteclere
Author-email: hauteclere.code@gmail.com
License: MIT
Classifier: License :: OSI Approved :: MIT License
Classifier: Programming Language :: Python :: 3.10
Classifier: Operating System :: OS Independent
Requires-Python: >=3.10
License-File: LICENSE
Requires-Dist: Jinja2 (>=3.1.2)
Requires-Dist: MarkupSafe (>=2.1.2)
Requires-Dist: pydantic (>=1.10.6)
Requires-Dist: typing-extensions (>=4.5.0)
Provides-Extra: dev
Requires-Dist: twine (>=4.0.2) ; extra == 'dev'
